qt_extensions/__init__.py
qt_extensions/box.py
qt_extensions/button.py
qt_extensions/combobox.py
qt_extensions/elementbrowser.py
qt_extensions/elide_label.py
qt_extensions/filebrowser.py
qt_extensions/flexview.py
qt_extensions/helper.py
qt_extensions/logger.py
qt_extensions/mainwindow.py
qt_extensions/messagebox.py
qt_extensions/resizegrip.py
qt_extensions/scrollarea.py
qt_extensions/testing.py
qt_extensions/theme.py
qt_extensions/typeutils.py
qt_extensions/viewer.py
qt_extensions/parameters/__init__.py
qt_extensions/parameters/editor.py
qt_extensions/parameters/tabdata.py
qt_extensions/parameters/widgets.py
qt_extensions-1.2.1.dist-info/LICENSE
qt_extensions-1.2.1.dist-info/METADATA
qt_extensions-1.2.1.dist-info/WHEEL
qt_extensions-1.2.1.dist-info/top_level.txt
qt_extensions-1.2.1.dist-info/RECORD
