Metadata-Version: 2.1
Name: qt-extensions
Version: 1.2.1
Summary: Various QtWidgets extending the functionality of PySide2
Author: Beat Reichenbach
License: MIT
Requires-Python: <3.11,>=3.9
License-File: LICENSE
Requires-Dist: PySide2<6,>=5.15
Requires-Dist: qt-material-icons<1,>=0.2
Provides-Extra: dev
Requires-Dist: black>=24.0; extra == "dev"
Requires-Dist: python-semantic-release>=9.0; extra == "dev"
